reddit/__init__.py
reddit/reddit.py
py_reddit-1.1.12.dist-info/LICENSE
py_reddit-1.1.12.dist-info/METADATA
py_reddit-1.1.12.dist-info/WHEEL
py_reddit-1.1.12.dist-info/top_level.txt
py_reddit-1.1.12.dist-info/RECORD
