Metadata-Version: 2.1
Name: py-reddit
Version: 1.1.12
Summary: Reddit and python, made simple.
Author: KING7077
Author-email: sram2007india@gmail.com
License: MIT
Keywords: python,reddit,py-reddit,async-py-reddit,python-reddit
Platform: UNKNOWN
Classifier: Programming Language :: Python :: 3
Classifier: License :: OSI Approved :: MIT License
Classifier: Operating System :: Unix
Requires-Python: >=3.6
License-File: LICENSE
Requires-Dist: aiohttp
Requires-Dist: requests
